clisn/__init__.py
clisn/manager.py
clisn/namespaces.py
clisn-0.1.4.dist-info/LICENSE
clisn-0.1.4.dist-info/METADATA
clisn-0.1.4.dist-info/WHEEL
clisn-0.1.4.dist-info/RECORD
