Metadata-Version: 2.1
Name: clisn
Version: 0.1.4
Summary: 
Author: Lukas Plank
Author-email: lupl@tuta.io
Requires-Python: >=3.11,<4.0
Classifier: Programming Language :: Python :: 3
Classifier: Programming Language :: Python :: 3.11
Requires-Dist: rdflib (>=7.0.0,<8.0.0)
